MANIFEST.in
README.rst
setup.py
waitredis/__init__.py
waitredis.egg-info/PKG-INFO
waitredis.egg-info/SOURCES.txt
waitredis.egg-info/dependency_links.txt
waitredis.egg-info/entry_points.txt
waitredis.egg-info/not-zip-safe
waitredis.egg-info/requires.txt
waitredis.egg-info/top_level.txt