Metadata-Version: 1.0
Name: waitredis
Version: 0.1
Summary: Simple wrapper script to wait until redis is ready
Home-page: https://github.com/Stupeflix/waitredis
Author: Luper Rouch
Author-email: luper.rouch@gmail.com
License: BSD
Keywords: redis wrapper-script
Platform: UNKNOWN
